README.md
setup.cfg
setup.py
kaggle_fastai_custom_metrics/Optimiser_AUC.py
kaggle_fastai_custom_metrics/__init__.py
kaggle_fastai_custom_metrics/kfcm.py
kaggle_fastai_custom_metrics.egg-info/PKG-INFO
kaggle_fastai_custom_metrics.egg-info/SOURCES.txt
kaggle_fastai_custom_metrics.egg-info/dependency_links.txt
kaggle_fastai_custom_metrics.egg-info/requires.txt
kaggle_fastai_custom_metrics.egg-info/top_level.txt