Metadata-Version: 2.1
Name: kaggle-fastai-custom-metrics
Version: 1.0.2
Summary: Custom Metrics for fastai v1 for kaggle competitions
Home-page: https://shadabsayeed.tech/2020-09-08-CustomMetrics/
Author: shadab_sayeed
Author-email: shadabsayeedxxx@gmail.com
License: MIT
Download-URL: https://github.com/shadab4150/kaggle_fastai_custom_metrics/archive/v1.0.2.tar.gz
Keywords: Fastai,Competition Metrics,Kaggle
Platform: UNKNOWN
Classifier: Programming Language :: Python :: 3
Classifier: License :: OSI Approved :: MIT License
Classifier: Operating System :: OS Independent
